mcp_ai_forever/__init__.py
mcp_ai_forever/__main__.py
mcp_ai_forever/debug.py
mcp_ai_forever/i18n.py
mcp_ai_forever/py.typed
mcp_ai_forever/server.py
mcp_ai_forever/desktop_app/__init__.py
mcp_ai_forever/desktop_app/desktop_app.py
mcp_ai_forever/desktop_release/__init__.py
mcp_ai_forever/desktop_release/mcp-feedback-enhanced-desktop-linux
mcp_ai_forever/desktop_release/mcp-feedback-enhanced-desktop-macos-arm64
mcp_ai_forever/desktop_release/mcp-feedback-enhanced-desktop-macos-intel
mcp_ai_forever/desktop_release/mcp-feedback-enhanced-desktop.exe
mcp_ai_forever/utils/__init__.py
mcp_ai_forever/utils/error_handler.py
mcp_ai_forever/utils/memory_monitor.py
mcp_ai_forever/utils/resource_manager.py
mcp_ai_forever/web/__init__.py
mcp_ai_forever/web/main.py
mcp_ai_forever/web/auth/__init__.py
mcp_ai_forever/web/auth/auth_manager.py
mcp_ai_forever/web/auth/database.py
mcp_ai_forever/web/constants/__init__.py
mcp_ai_forever/web/constants/message_codes.py
mcp_ai_forever/web/locales/en/translation.json
mcp_ai_forever/web/locales/zh-CN/translation.json
mcp_ai_forever/web/locales/zh-TW/translation.json
mcp_ai_forever/web/models/__init__.py
mcp_ai_forever/web/models/feedback_result.py
mcp_ai_forever/web/models/feedback_session.py
mcp_ai_forever/web/routes/__init__.py
mcp_ai_forever/web/routes/auth_routes.py
mcp_ai_forever/web/routes/main_routes.py
mcp_ai_forever/web/static/favicon.ico
mcp_ai_forever/web/static/icon-192.png
mcp_ai_forever/web/static/icon.svg
mcp_ai_forever/web/static/index.html
mcp_ai_forever/web/static/css/audio-management.css
mcp_ai_forever/web/static/css/notification-settings.css
mcp_ai_forever/web/static/css/prompt-management.css
mcp_ai_forever/web/static/css/session-management.css
mcp_ai_forever/web/static/css/styles.css
mcp_ai_forever/web/static/js/app.js
mcp_ai_forever/web/static/js/i18n.js
mcp_ai_forever/web/static/js/modules/connection-monitor.js
mcp_ai_forever/web/static/js/modules/file-upload-manager.js
mcp_ai_forever-2.6.6.dist-info/METADATA
mcp_ai_forever-2.6.6.dist-info/WHEEL
mcp_ai_forever-2.6.6.dist-info/entry_points.txt
mcp_ai_forever-2.6.6.dist-info/licenses/LICENSE
mcp_ai_forever-2.6.6.dist-info/RECORD
